{
  "$schema": "https://mintlify.com/docs.json",
  "theme": "mint",
  "name": "Mint Starter Kit",
  "colors": {
    "primary": "#16A34A",
    "light": "#07C983",
    "dark": "#15803D"
  },
  "favicon": "/favicon.svg",
  "navigation": {
    "tabs": [
      {
        "tab": "开始使用",
        "groups": [
          {
            "group": "Get Started",
            "pages": [
              "index"
            ]
          },
          {
            "group": "运维项目",
            "pages": [
              {
                "group": "企业级自动化部署平台搭建",
                "icon": "robot",
                "pages": [
                  "cicd/01",
                  "cicd/02"
                ]
              },
              {
                "group": "全链路监控+日志收集系统建设",
                "icon": "tag",
                "pages": [
                  "prometheus/01",
                  "prometheus/02"
                ]
              },
              {
                "group": "K8S容器化改造与CI/CD流程优化",
                "icon": "square-terminal",
                "pages": [
                  "k8s-cicd/01",
                  "k8s-cicd/02"
                ]
              },
              {
                "group": "CMDB资产管理平台",
                "icon": "calendar-days",
                "pages": [
                  "cmdb/01",
                  "cmdb/02"
                ]
              }           
            ]
          }
        ]
      }
    ]
  },
  "logo": {
    "light": "logo/light.webp",
    "dark": "logo/dark.webp"
  }
}